Workbook

Sheet 1 Assumptions
A1: STARBUCKS CORPORATION (SBUX) — DCF VALUATION MODEL | KEY ASSUMPTIONS
A3: REVENUE GROWTH ASSUMPTIONS | B3: Input Value | C3: WACC INPUTS | D3: Input Value
A4: FY2025E Revenue Growth Rate | B4: 0.03 | C4: Risk-Free Rate (10Y UST) | D4: 0.04054
A5: FY2026E Revenue Growth Rate | B5: 0.05 | C5: Equity Risk Premium (ERP) | D5: 0.055
A6: FY2027E Revenue Growth Rate | B6: 0.06 | C6: Levered Beta (5Y Monthly) | D6: 0.95
A7: FY2028E Revenue Growth Rate | B7: 0.07 | C7: Pre-Tax Cost of Debt | D7: 0.0455
A8: FY2029E Revenue Growth Rate | B8: 0.07 | C8: Effective Tax Rate (for WACC) | D8: 0.248
A9: FY2030E Revenue Growth Rate | B9: 0.06 | C9: Total Debt ($M) | D9: 23805
A10: FY2031E Revenue Growth Rate | B10: 0.055 | C10: Cash & Equivalents ($M) | D10: 3183
A11: FY2032E Revenue Growth Rate | B11: 0.05 | C11: Shares Outstanding (M) | D11: 1132.6
A12: FY2033E Revenue Growth Rate | B12: 0.045 | C12: Current Stock Price ($) | D12: 84
A13: FY2034E Revenue Growth Rate | B13: 0.04
A14: Terminal Growth Rate (g) | B14: 0.025 | C14: SENSITIVITY RANGES | D14: Input Value
C15: WACC Sensitivity – Low Offset | D15: -0.02
A16: MARGIN ASSUMPTIONS | B16: Input Value | C16: WACC Sensitivity – High Offset | D16: 0.02
A17: EBITDA Margin (% of Revenue) | B17: 0.175 | C17: TGR Sensitivity – Low Offset | D17: -0.01
A18: D&A (% of Revenue) | B18: 0.043 | C18: TGR Sensitivity – High Offset | D18: 0.01
A19: Capex (% of Revenue) | B19: 0.063
A20: Change in NWC (% of Revenue) | B20: 0.005
A21: Effective Tax Rate | B21: 0.248

Sheet 2 Historical
A1: STARBUCKS CORPORATION — HISTORICAL FINANCIAL DATA (FY2020–FY2024) | Source: SBUX 10-K / SEC Filings (in $M)
A2: Income Statement Metrics | B2: FY2020 | C2: FY2021 | D2: FY2022 | E2: FY2023 | F2: FY2024 | G2: 5Y CAGR
A3: Total Net Revenue ($M) | B3: 23518 | C3: 29061 | D3: 32250.3 | E3: 35975.6 | F3: 36176.2 | G3: =(F3/B3)^(1/4)-1 -> 0.11366774
A4: EBITDA ($M) | B4: 2818 | C4: 4847 | D4: 5907.9 | E4: 6545 | F4: 5016 | G4: =(F4/B4)^(1/4)-1 -> 0.15505891
A5: Depreciation & Amortization ($M) | B5: 1450.3 | C5: 1524.1 | D5: 1529.4 | E5: 1450.3 | F5: 1592.4 | G5: =(F5/B5)^(1/4)-1 -> 0.02364314
A6: EBIT (Operating Income) ($M) | B6: 1367.7 | C6: 4200.3 | D6: 4378.5 | E6: 3094.7 | F6: 3423.9 | G6: =(F6/B6)^(1/4)-1 -> 0.25786072
A7: Interest Expense ($M) | B7: 600.9 | C7: 466.1 | D7: 468.9 | E7: 481.4 | F7: 554.4 | G7: =(F7/B7)^(1/4)-1 -> -0.019934155
A8: EBT (Pre-tax Income) ($M) | B8: 767.5 | C8: 4231.9 | D8: 4378.5 | E8: 2507.3 | F8: 2249.8 | G8: =(F8/B8)^(1/4)-1 -> 0.30847787
A9: Taxes ($M) | B9: 218.1 | C9: 948.5 | D9: 1277.2 | E9: 650.6 | F9: 880.8 | G9: =(F9/B9)^(1/4)-1 -> 0.41760557
A10: Net Income ($M) | B10: 928.3 | C10: 3283.4 | D10: 3281.6 | E10: 1856.4 | F10: 1368.9 | G10: =(F10/B10)^(1/4)-1 -> 0.10197272
A11: EPS – Diluted ($) | B11: 0.79 | C11: 2.83 | D11: 2.95 | E11: 1.69 | F11: 1.24 | G11: =(F11/B11)^(1/4)-1 -> 0.11930553
A13: Cash Flow & Balance Sheet Metrics | B13: FY2020 | C13: FY2021 | D13: FY2022 | E13: FY2023 | F13: FY2024 | G13: Notes
A14: Capital Expenditures ($M) | B14: 1444.9 | C14: 1470 | D14: 1841.3 | E14: 2333.6 | F14: 2445.6 | G14: Source: 10-K / SEC EDGAR
A15: Change in Net Working Capital ($M) | B15: 320 | C15: 180 | D15: 215 | E15: 270 | F15: 310
A16: Total Debt ($M) | B16: 16213 | C16: 16557 | D16: 17332 | E16: 16066 | F16: 23805
A17: Cash & Equivalents ($M) | B17: 2965.6 | C17: 3345.4 | D17: 3020.7 | E17: 3561.8 | F17: 3183
A18: Net Debt ($M) | B18: =B16-B17 -> 13247.4 | C18: =C16-C17 -> 13211.6 | D18: =D16-D17 -> 14311.3 | E18: =E16-E17 -> 12504.2 | F18: =F16-F17 -> 20622
A19: Shares Outstanding – Diluted (M) | B19: 1175.7 | C19: 1160.4 | D19: 1143.5 | E19: 1131.6 | F19: 1132.6
A22: Margin & Ratio Analysis (Computed) | B22: FY2020 | C22: FY2021 | D22: FY2022 | E22: FY2023 | F22: FY2024
A23: EBITDA Margin | B23: =B4/B3 -> 0.11982311 | C23: =C4/C3 -> 0.1667871 | D23: =D4/D3 -> 0.18318899 | E23: =E4/E3 -> 0.18192886 | F23: =F4/F3 -> 0.1386547
A24: EBIT Margin | B24: =B7/B3 -> 0.025550642 | C24: =C7/C3 -> 0.016038677 | D24: =D7/D3 -> 0.0145394 | E24: =E7/E3 -> 0.013381292 | F24: =F7/F3 -> 0.015324993
A25: Net Income Margin | B25: =B11/B3 -> 3.3591292e-05 | C25: =C11/C3 -> 9.738137e-05 | D25: =D11/D3 -> 9.1472017e-05 | E25: =E11/E3 -> 4.6976284e-05 | F25: =F11/F3 -> 3.4276679e-05
A26: Capex / Revenue | B26: =B14/B3 -> 0.061438047 | C26: =C14/C3 -> 0.050583256 | D26: =D14/D3 -> 0.057094043 | E26: =E14/E3 -> 0.064866187 | F26: =F14/F3 -> 0.067602457
A27: D&A / Revenue | B27: =B5/B3 -> 0.061667659 | C27: =C5/C3 -> 0.052444857 | D27: =D5/D3 -> 0.047422815 | E27: =E5/E3 -> 0.040313435 | F27: =F5/F3 -> 0.04401789
A28: Tax Rate (ETR) | B28: =B10/B9 -> 4.2563044 | C28: =C10/C9 -> 3.4616763 | D28: =D10/D9 -> 2.5693705 | E28: =E10/E9 -> 2.8533661 | F28: =F10/F9 -> 1.5541553

Sheet 3 Forecast FCFF
A1: STARBUCKS CORPORATION — FORECAST MODEL & FREE CASH FLOW TO FIRM (FY2025E–FY2034E) | All figures in $M
A2: Driver / Line Item | B2: FY2025E | C2: FY2026E | D2: FY2027E | E2: FY2028E | F2: FY2029E | G2: FY2030E | H2: FY2031E | I2: FY2032E | J2: FY2033E | K2: FY2034E
A3: Revenue Growth Rate (%) | B3: ='1 Assumptions'!B4 -> 0.03 | C3: ='1 Assumptions'!B5 -> 0.05 | D3: ='1 Assumptions'!B6 -> 0.06 | E3: ='1 Assumptions'!B7 -> 0.07 | F3: ='1 Assumptions'!B8 -> 0.07 | G3: ='1 Assumptions'!B9 -> 0.06 | H3: ='1 Assumptions'!B10 -> 0.055 | I3: ='1 Assumptions'!B11 -> 0.05 | J3: ='1 Assumptions'!B12 -> 0.045 | K3: ='1 Assumptions'!B13 -> 0.04
A4: Total Net Revenue ($M) | B4: ='2 Historical'!F3*(1+B3) -> 37261.486 | C4: =B4*(1+C3) -> 39124.56 | D4: =C4*(1+D3) -> 41472.034 | E4: =D4*(1+E3) -> 44375.076 | F4: =E4*(1+F3) -> 47481.332 | G4: =F4*(1+G3) -> 50330.212 | H4: =G4*(1+H3) -> 53098.373 | I4: =H4*(1+I3) -> 55753.292 | J4: =I4*(1+J3) -> 58262.19 | K4: =J4*(1+K3) -> 60592.678
A5: EBITDA ($M) | B5: =B4*'1 Assumptions'!$B$17 -> 6520.76 | C5: =C4*'1 Assumptions'!$B$17 -> 6846.7981 | D5: =D4*'1 Assumptions'!$B$17 -> 7257.6059 | E5: =E4*'1 Assumptions'!$B$17 -> 7765.6384 | F5: =F4*'1 Assumptions'!$B$17 -> 8309.233 | G5: =G4*'1 Assumptions'!$B$17 -> 8807.787 | H5: =H4*'1 Assumptions'!$B$17 -> 9292.2153 | I5: =I4*'1 Assumptions'!$B$17 -> 9756.8261 | ... K5: =K4*'1 Assumptions'!$B$17 -> 10603.719
A6: Depreciation & Amortization ($M) | B6: =B4*'1 Assumptions'!$B$18 -> 1602.2439 | C6: =C4*'1 Assumptions'!$B$18 -> 1682.3561 | D6: =D4*'1 Assumptions'!$B$18 -> 1783.2975 | E6: =E4*'1 Assumptions'!$B$18 -> 1908.1283 | F6: =F4*'1 Assumptions'!$B$18 -> 2041.6973 | G6: =G4*'1 Assumptions'!$B$18 -> 2164.1991 | H6: =H4*'1 Assumptions'!$B$18 -> 2283.23 | I6: =I4*'1 Assumptions'!$B$18 -> 2397.3915 | ... K6: =K4*'1 Assumptions'!$B$18 -> 2605.4851
A7: EBIT (Operating Income) ($M) | B7: =B5-B6 -> 4918.5162 | C7: =C5-C6 -> 5164.442 | D7: =D5-D6 -> 5474.3085 | E7: =E5-E6 -> 5857.5101 | F7: =F5-F6 -> 6267.5358 | G7: =G5-G6 -> 6643.5879 | H7: =H5-H6 -> 7008.9853 | I7: =I5-I6 -> 7359.4345 | ... K7: =K5-K6 -> 7998.2334
A8: Taxes on EBIT ($M) | B8: =B7*'1 Assumptions'!$B$21 -> 1219.792 | C8: =C7*'1 Assumptions'!$B$21 -> 1280.7816 | D8: =D7*'1 Assumptions'!$B$21 -> 1357.6285 | E8: =E7*'1 Assumptions'!$B$21 -> 1452.6625 | F8: =F7*'1 Assumptions'!$B$21 -> 1554.3489 | G8: =G7*'1 Assumptions'!$B$21 -> 1647.6098 | H8: =H7*'1 Assumptions'!$B$21 -> 1738.2283 | I8: =I7*'1 Assumptions'!$B$21 -> 1825.1398 | ... K8: =K7*'1 Assumptions'!$B$21 -> 1983.5619
A9: NOPAT = EBIT × (1–Tax Rate) ($M) | B9: =B7*(1-'1 Assumptions'!$B$21) -> 3698.7241 | C9: =C7*(1-'1 Assumptions'!$B$21) -> 3883.6604 | D9: =D7*(1-'1 Assumptions'!$B$21) -> 4116.68 | E9: =E7*(1-'1 Assumptions'!$B$21) -> 4404.8476 | F9: =F7*(1-'1 Assumptions'!$B$21) -> 4713.1869 | G9: =G7*(1-'1 Assumptions'!$B$21) -> 4995.9781 | H9: =H7*(1-'1 Assumptions'!$B$21) -> 5270.7569 | I9: =I7*(1-'1 Assumptions'!$B$21) -> 5534.2948 | ... K9: =K7*(1-'1 Assumptions'!$B$21) -> 6014.6715
A11: FREE CASH FLOW TO FIRM (FCFF) BRIDGE | B11: FY2025E | C11: FY2026E | D11: FY2027E | E11: FY2028E | F11: FY2029E | G11: FY2030E | H11: FY2031E | I11: FY2032E | J11: FY2033E | K11: FY2034E
A12: (+) Depreciation & Amortization ($M) | B12: =B6 -> 1602.2439 | C12: =C6 -> 1682.3561 | D12: =D6 -> 1783.2975 | E12: =E6 -> 1908.1283 | F12: =F6 -> 2041.6973 | G12: =G6 -> 2164.1991 | H12: =H6 -> 2283.23 | I12: =I6 -> 2397.3915 | ... K12: =K6 -> 2605.4851
A13: (–) Capital Expenditures ($M) | B13: =-B4*'1 Assumptions'!$B$19 -> -2347.4736 | C13: =-C4*'1 Assumptions'!$B$19 -> -2464.8473 | D13: =-D4*'1 Assumptions'!$B$19 -> -2612.7381 | E13: =-E4*'1 Assumptions'!$B$19 -> -2795.6298 | F13: =-F4*'1 Assumptions'!$B$19 -> -2991.3239 | G13: =-G4*'1 Assumptions'!$B$19 -> -3170.8033 | H13: =-H4*'1 Assumptions'!$B$19 -> -3345.1975 | I13: =-I4*'1 Assumptions'!$B$19 -> -3512.4574 | ... K13: =-K4*'1 Assumptions'!$B$19 -> -3817.3387
A14: (–) Change in Net Working Capital ($M) | B14: =-B4*'1 Assumptions'!$B$20 -> -186.30743 | C14: =-C4*'1 Assumptions'!$B$20 -> -195.6228 | D14: =-D4*'1 Assumptions'!$B$20 -> -207.36017 | E14: =-E4*'1 Assumptions'!$B$20 -> -221.87538 | F14: =-F4*'1 Assumptions'!$B$20 -> -237.40666 | G14: =-G4*'1 Assumptions'!$B$20 -> -251.65106 | H14: =-H4*'1 Assumptions'!$B$20 -> -265.49187 | I14: =-I4*'1 Assumptions'!$B$20 -> -278.76646 | ... K14: =-K4*'1 Assumptions'!$B$20 -> -302.96339
A15: FREE CASH FLOW TO FIRM – FCFF ($M) | B15: =B9+B12+B13+B14 -> 2767.187 | C15: =C9+C12+C13+C14 -> 2905.5463 | D15: =D9+D12+D13+D14 -> 3079.8791 | E15: =E9+E12+E13+E14 -> 3295.4707 | F15: =F9+F12+F13+F14 -> 3526.1536 | G15: =G9+G12+G13+G14 -> 3737.7228 | H15: =H9+H12+H13+H14 -> 3943.2976 | I15: =I9+I12+I13+I14 -> 4140.4625 | ... K15: =K9+K12+K13+K14 -> 4499.8546
A17: MARGIN CHECKS | B17: FY2025E | C17: FY2026E | D17: FY2027E | E17: FY2028E | F17: FY2029E | G17: FY2030E | H17: FY2031E | I17: FY2032E | J17: FY2033E | K17: FY2034E
A18: EBITDA Margin (%) | B18: =B5/B4 -> 0.175 | C18: =C5/C4 -> 0.175 | D18: =D5/D4 -> 0.175 | E18: =E5/E4 -> 0.175 | F18: =F5/F4 -> 0.175 | G18: =G5/G4 -> 0.175 | H18: =H5/H4 -> 0.175 | I18: =I5/I4 -> 0.175 | ... K18: =K5/K4 -> 0.175
A19: FCFF Margin (%) | B19: =B15/B4 -> 0.074264 | C19: =C15/C4 -> 0.074264 | D19: =D15/D4 -> 0.074264 | E19: =E15/E4 -> 0.074264 | F19: =F15/F4 -> 0.074264 | G19: =G15/G4 -> 0.074264 | H19: =H15/H4 -> 0.074264 | I19: =I15/I4 -> 0.074264 | ... K19: =K15/K4 -> 0.074264
A20: Capex / Revenue (%) | B20: =ABS(B13)/B4 -> 0.063 | C20: =ABS(C13)/C4 -> 0.063 | D20: =ABS(D13)/D4 -> 0.063 | E20: =ABS(E13)/E4 -> 0.063 | F20: =ABS(F13)/F4 -> 0.063 | G20: =ABS(G13)/G4 -> 0.063 | H20: =ABS(H13)/H4 -> 0.063 | I20: =ABS(I13)/I4 -> 0.063 | ... K20: =ABS(K13)/K4 -> 0.063

Sheet 4 WACC
A1: STARBUCKS CORPORATION — WACC CALCULATION | CAPM-Based Cost of Equity
A3: STEP 1 — COST OF EQUITY (CAPM) | B3: Value | C3: Formula Reference | D3: Note
A4: Risk-Free Rate (Rf) | B4: ='1 Assumptions'!B4 -> 0.03 | C4: 1_Assumptions!B4 | D4: 10Y US Treasury Yield
A5: Equity Risk Premium (ERP) | B5: ='1 Assumptions'!B5 -> 0.05 | C5: 1_Assumptions!B5 | D5: Damodaran ERP estimate
A6: Levered Beta (β) | B6: ='1 Assumptions'!B6 -> 0.06 | C6: 1_Assumptions!B6 | D6: 5Y Monthly vs S&P 500
A7: Cost of Equity (Ke) = Rf + β × ERP | B7: =B4+B6*B5 -> 0.033 | C7: Rf + Beta x ERP | D7: CAPM formula
A9: STEP 2 — AFTER-TAX COST OF DEBT | B9: Value | C9: Formula Reference | D9: Note
A10: Pre-Tax Cost of Debt (Kd) | B10: ='1 Assumptions'!B8 -> 0.07 | C10: 1_Assumptions!B8 | D10: Blended yield on SBUX bonds
A11: Effective Tax Rate | B11: ='1 Assumptions'!B9 -> 0.06 | C11: 1_Assumptions!B9 | D11: Used for tax shield
A12: After-Tax Cost of Debt = Kd × (1–Tax Rate) | B12: =B10*(1-B11) -> 0.0658 | C12: Kd x (1-Tax) | D12: Interest tax shield benefit
A14: STEP 3 — CAPITAL STRUCTURE WEIGHTS | B14: Value ($M or %) | C14: Formula Reference | D14: Note
A15: Total Debt ($M) | B15: ='1 Assumptions'!B10 -> 0.055 | C15: 1_Assumptions!B10 | D15: Book value of debt
A16: Cash & Equivalents ($M) | B16: ='1 Assumptions'!B11 -> 0.05 | C16: 1_Assumptions!B11 | D16: Most recent quarter
A17: Shares Outstanding (M) | B17: ='1 Assumptions'!B12 -> 0.045 | C17: 1_Assumptions!B12 | D17: Diluted share count
A18: Current Stock Price ($) | B18: ='1 Assumptions'!B13 -> 0.04 | C18: 1_Assumptions!B13 | D18: Market price for equity value
A19: Market Capitalization ($M) | B19: =B17*B18 -> 0.0018 | C19: Market Cap / (MktCap + Debt) | D19: Market-value equity
A20: Enterprise Value (Pre-DCF) ($M) | B20: =B19+B15-B16 -> 0.0068 | C20: Market Cap / (MktCap + Debt) | D20: For weight calculation
A21: Weight of Equity (E/V) | B21: =B19/(B19+B15) -> 0.031690141 | C21: Mkt Cap = Shares x Price | D21: Market-value weights
A22: Weight of Debt (D/V) | B22: =B15/(B19+B15) -> 0.96830986 | C22: EV = MktCap + Debt - Cash | D22: Market-value weights
A24: STEP 4 — WACC CALCULATION | B24: Value | C24: Formula | D24: Note
A25: Equity Component (Ke × We) | B25: =B7*B21 -> 0.0010457746 | C25: Ke x We
A26: Debt Component (Kd_AT × Wd) | B26: =B12*B22 -> 0.063714789 | C26: Kd_AT x Wd
A27: WACC = Ke×We + Kd_AT×Wd | B27: =B25+B26 -> 0.064760563 | C27: Ke x We + Kd_AT x Wd | D27: PRIMARY DISCOUNT RATE

Sheet 5 DCF Valuation
A1: STARBUCKS CORPORATION — DCF VALUATION | Unlevered DCF (FCFF Method) | All figures in $M unless noted
A2: Line Item | B2: FY2025E | C2: FY2026E | D2: FY2027E | E2: FY2028E | F2: FY2029E | G2: FY2030E | H2: FY2031E | I2: FY2032E | J2: FY2033E | K2: FY2034E
A3: WACC (Discount Rate) | B3: ='4 WACC'!B27 -> 0.064760563 | C3: ='4 WACC'!B27 -> 0.064760563 | D3: ='4 WACC'!B27 -> 0.064760563 | E3: ='4 WACC'!B27 -> 0.064760563 | F3: ='4 WACC'!B27 -> 0.064760563 | G3: ='4 WACC'!B27 -> 0.064760563 | H3: ='4 WACC'!B27 -> 0.064760563 | I3: ='4 WACC'!B27 -> 0.064760563 | J3: ='4 WACC'!B27 -> 0.064760563 | K3: ='4 WACC'!B27 -> 0.064760563
A4: FCFF ($M) | B4: ='3 Forecast FCFF'!B15 -> 2767.187 | C4: ='3 Forecast FCFF'!C15 -> 2905.5463 | D4: ='3 Forecast FCFF'!D15 -> 3079.8791 | E4: ='3 Forecast FCFF'!E15 -> 3295.4707 | F4: ='3 Forecast FCFF'!F15 -> 3526.1536 | G4: ='3 Forecast FCFF'!G15 -> 3737.7228 | H4: ='3 Forecast FCFF'!H15 -> 3943.2976 | I4: ='3 Forecast FCFF'!I15 -> 4140.4625 | ... K4: ='3 Forecast FCFF'!K15 -> 4499.8546
A5: Discount Period (Mid-Year Convention) | B5: =0+0.5 -> 0.5 | C5: =1+0.5 -> 1.5 | D5: =2+0.5 -> 2.5 | E5: =3+0.5 -> 3.5 | F5: =4+0.5 -> 4.5 | G5: =5+0.5 -> 5.5 | H5: =6+0.5 -> 6.5 | I5: =7+0.5 -> 7.5 | J5: =8+0.5 -> 8.5 | K5: =9+0.5 -> 9.5
A6: Discount Factor = 1 / (1+WACC)^t | B6: =1/(1+B3)^B5 -> 0.96911211 | C6: =1/(1+B3)^C5 -> 0.91016905 | D6: =1/(1+B3)^D5 -> 0.85481101 | E6: =1/(1+B3)^E5 -> 0.80281994 | F6: =1/(1+B3)^F5 -> 0.75399105 | G6: =1/(1+B3)^G5 -> 0.70813202 | H6: =1/(1+B3)^H5 -> 0.66506222 | I6: =1/(1+B3)^I5 -> 0.62461199 | J6: =1/(1+B3)^J5 -> 0.58662202 | K6: =1/(1+B3)^K5 -> 0.55094266
A7: PV of FCFF ($M) | B7: =B4*B6 -> 2681.7144 | C7: =C4*C6 -> 2644.5384 | D7: =D4*D6 -> 2632.7146 | E7: =E4*E6 -> 2645.6696 | F7: =F4*F6 -> 2658.6883 | G7: =G4*G6 -> 2646.8012 | H7: =H4*H6 -> 2622.5382 | I7: =I4*I6 -> 2586.1825 | ... K7: =K4*K6 -> 2479.1619
A9: TERMINAL VALUE CALCULATION (Gordon Growth Model)
A10: Terminal Growth Rate (g) | B10: ='1 Assumptions'!B14 -> 0.025
A11: FCFF in Terminal Year (FY2034E) | B11: =K4 -> 4499.8546
A12: FCFF × (1+g) — Normalized Year | B12: =B11*(1+B10) -> 4612.351
A13: Terminal Value = FCFF×(1+g) / (WACC–g) | B13: =B12/(B3-B10) -> 116003.16
A14: Discount Factor at End of Year 10 | B14: =1/(1+B3)^10 -> 0.53392521
A15: PV of Terminal Value ($M) | B15: =B13*B14 -> 61937.011
A17: ENTERPRISE VALUE BRIDGE
A18: Sum of PV of FCFFs (FY2025–FY2034) | B18: =SUM(B7:K7) -> 26136.195
A19: PV of Terminal Value | B19: =B15 -> 61937.011
A20: Enterprise Value (EV) | B20: =B18+B19 -> 88073.207
A21: (–) Total Net Debt ($M) | B21: ='4 WACC'!B15-'4 WACC'!B16 -> 0.005
A22: Equity Value ($M) | B22: =B20-B21 -> 88073.202
A23: ÷ Diluted Shares Outstanding (M) | B23: ='4 WACC'!B17 -> 0.045
A24: IMPLIED SHARE PRICE ($) | B24: =B22/B23 -> 1957182.3
A25: Current Market Price ($) | B25: ='1 Assumptions'!B13 -> 0.04
A26: Premium / (Discount) to Market | B26: =B24/B25-1 -> 48929555
A28: ENTERPRISE VALUE COMPOSITION
A29: PV of FCFFs ($M) | B29: =B18 -> 26136.195
A30: % of Enterprise Value | B30: =B29/B20 -> 0.29675535
A31: PV of Terminal Value ($M) | B31: =B15 -> 61937.011
A32: % of Enterprise Value | B32: =B31/B20 -> 0.70324465

Sheet 6 Sensitivity Dashboard
A1: STARBUCKS CORPORATION (SBUX) — DCF VALUATION DASHBOARD & SENSITIVITY ANALYSIS
A3: VALUATION SUMMARY
A4: Implied Share Price | B4: ='5 DCF Valuation'!B24 -> 1957182.3
A5: Enterprise Value ($M) | B5: ='5 DCF Valuation'!B20 -> 88073.207
A6: Equity Value ($M) | B6: ='5 DCF Valuation'!B22 -> 88073.202
A7: WACC | B7: ='4 WACC'!B27 -> 0.064760563
A8: Terminal Growth Rate | B8: ='1 Assumptions'!B14 -> 0.025
A9: PV of FCFFs ($M) | B9: ='5 DCF Valuation'!B29 -> 26136.195
A10: PV of Terminal Value ($M) | B10: ='5 DCF Valuation'!B31 -> 61937.011
A11: TV as % of EV | B11: ='5 DCF Valuation'!B32 -> 0.70324465
A12: Current Market Price | B12: ='1 Assumptions'!B13 -> 0.04
A13: Upside / (Downside) | B13: ='5 DCF Valuation'!B26 -> 48929555
A14: FY2024 Revenue ($M) | B14: ='2 Historical'!F3 -> 36176.2
A15: FY2024 EBITDA ($M) | B15: ='2 Historical'!F4 -> 5016
A17: SENSITIVITY ANALYSIS — IMPLIED SHARE PRICE ($) vs. WACC & TERMINAL GROWTH RATE
A18: WACC → | B18: ='4 WACC'!B27+(-0.02) -> 0.044760563 | C18: ='4 WACC'!B27+(-0.01) -> 0.054760563 | D18: ='4 WACC'!B27+(0) -> 0.064760563 | E18: ='4 WACC'!B27+(0.01) -> 0.074760563 | F18: ='4 WACC'!B27+(0.02) -> 0.084760563 | G18: ← TGR Row Labels
A19: ='1 Assumptions'!B14+(-0.01) -> 0.015 | B19: =('3 Forecast FCFF'!B15/(1+B18)^0.5+'3 Forecast FCFF'!C15/(1+B18)^1.5+'3 Forecast FCFF'!D15/(1+B18)^2.5+'3 Forecast FCFF'!E15/(1+B18)^3.5+'3 Forecast FCFF'!F15/(1+B18)^4.5+'3 Forecast FCFF'!G15/(1+B18)^5.5+'3 Forecast FCFF'!H15/(1+B18)^6.5+'3 Forecast FCFF'!I15/(1+B18)^7.5+'3 Forecast FCFF'!J15/(1+B18)^8.5+'3 Forecast FCFF'!K15/(1+B18)^9.5+'3 Forecast FCFF'!K15*(1+A19)/(B18-A19)/(1+B18)^10-('4 WACC'!B15-'4 WACC'!B16))/'4 WACC'!B17 -> 2839954.4 | C19: =('3 Forecast FCFF'!B15/(1+C18)^0.5+'3 Forecast FCFF'!C15/(1+C18)^1.5+'3 Forecast FCFF'!D15/(1+C18)^2.5+'3 Forecast FCFF'!E15/(1+C18)^3.5+'3 Forecast FCFF'!F15/(1+C18)^4.5+'3 Forecast FCFF'!G15/(1+C18)^5.5+'3 Forecast FCFF'!H15/(1+C18)^6.5+'3 Forecast FCFF'!I15/(1+C18)^7.5+'3 Forecast FCFF'!J15/(1+C18)^8.5+'3 Forecast FCFF'!K15/(1+C18)^9.5+'3 Forecast FCFF'!K15*(1+A19)/(C18-A19)/(1+C18)^10-('4 WACC'!B15-'4 WACC'!B16))/'4 WACC'!B17 -> 2106592.3 | D19: =('3 Forecast FCFF'!B15/(1+D18)^0.5+'3 Forecast FCFF'!C15/(1+D18)^1.5+'3 Forecast FCFF'!D15/(1+D18)^2.5+'3 Forecast FCFF'!E15/(1+D18)^3.5+'3 Forecast FCFF'!F15/(1+D18)^4.5+'3 Forecast FCFF'!G15/(1+D18)^5.5+'3 Forecast FCFF'!H15/(1+D18)^6.5+'3 Forecast FCFF'!I15/(1+D18)^7.5+'3 Forecast FCFF'!J15/(1+D18)^8.5+'3 Forecast FCFF'!K15/(1+D18)^9.5+'3 Forecast FCFF'!K15*(1+A19)/(D18-A19)/(1+D18)^10-('4 WACC'!B15-'4 WACC'!B16))/'4 WACC'!B17 -> 1669852.5 | E19: =('3 Forecast FCFF'!B15/(1+E18)^0.5+'3 Forecast FCFF'!C15/(1+E18)^1.5+'3 Forecast FCFF'!D15/(1+E18)^2.5+'3 Forecast FCFF'!E15/(1+E18)^3.5+'3 Forecast FCFF'!F15/(1+E18)^4.5+'3 Forecast FCFF'!G15/(1+E18)^5.5+'3 Forecast FCFF'!H15/(1+E18)^6.5+'3 Forecast FCFF'!I15/(1+E18)^7.5+'3 Forecast FCFF'!J15/(1+E18)^8.5+'3 Forecast FCFF'!K15/(1+E18)^9.5+'3 Forecast FCFF'!K15*(1+A19)/(E18-A19)/(1+E18)^10-('4 WACC'!B15-'4 WACC'!B16))/'4 WACC'!B17 -> 1380652 | F19: =('3 Forecast FCFF'!B15/(1+F18)^0.5+'3 Forecast FCFF'!C15/(1+F18)^1.5+'3 Forecast FCFF'!D15/(1+F18)^2.5+'3 Forecast FCFF'!E15/(1+F18)^3.5+'3 Forecast FCFF'!F15/(1+F18)^4.5+'3 Forecast FCFF'!G15/(1+F18)^5.5+'3 Forecast FCFF'!H15/(1+F18)^6.5+'3 Forecast FCFF'!I15/(1+F18)^7.5+'3 Forecast FCFF'!J15/(1+F18)^8.5+'3 Forecast FCFF'!K15/(1+F18)^9.5+'3 Forecast FCFF'!K15*(1+A19)/(F18-A19)/(1+F18)^10-('4 WACC'!B15-'4 WACC'!B16))/'4 WACC'!B17 -> 1175409.6
A20: ='1 Assumptions'!B14+(-0.005) -> 0.02 | B20: =('3 Forecast FCFF'!B15/(1+B18)^0.5+'3 Forecast FCFF'!C15/(1+B18)^1.5+'3 Forecast FCFF'!D15/(1+B18)^2.5+'3 Forecast FCFF'!E15/(1+B18)^3.5+'3 Forecast FCFF'!F15/(1+B18)^4.5+'3 Forecast FCFF'!G15/(1+B18)^5.5+'3 Forecast FCFF'!H15/(1+B18)^6.5+'3 Forecast FCFF'!I15/(1+B18)^7.5+'3 Forecast FCFF'!J15/(1+B18)^8.5+'3 Forecast FCFF'!K15/(1+B18)^9.5+'3 Forecast FCFF'!K15*(1+A20)/(B18-A20)/(1+B18)^10-('4 WACC'!B15-'4 WACC'!B16))/'4 WACC'!B17 -> 3297467.3 | C20: =('3 Forecast FCFF'!B15/(1+C18)^0.5+'3 Forecast FCFF'!C15/(1+C18)^1.5+'3 Forecast FCFF'!D15/(1+C18)^2.5+'3 Forecast FCFF'!E15/(1+C18)^3.5+'3 Forecast FCFF'!F15/(1+C18)^4.5+'3 Forecast FCFF'!G15/(1+C18)^5.5+'3 Forecast FCFF'!H15/(1+C18)^6.5+'3 Forecast FCFF'!I15/(1+C18)^7.5+'3 Forecast FCFF'!J15/(1+C18)^8.5+'3 Forecast FCFF'!K15/(1+C18)^9.5+'3 Forecast FCFF'!K15*(1+A20)/(C18-A20)/(1+C18)^10-('4 WACC'!B15-'4 WACC'!B16))/'4 WACC'!B17 -> 2330480.7 | D20: =('3 Forecast FCFF'!B15/(1+D18)^0.5+'3 Forecast FCFF'!C15/(1+D18)^1.5+'3 Forecast FCFF'!D15/(1+D18)^2.5+'3 Forecast FCFF'!E15/(1+D18)^3.5+'3 Forecast FCFF'!F15/(1+D18)^4.5+'3 Forecast FCFF'!G15/(1+D18)^5.5+'3 Forecast FCFF'!H15/(1+D18)^6.5+'3 Forecast FCFF'!I15/(1+D18)^7.5+'3 Forecast FCFF'!J15/(1+D18)^8.5+'3 Forecast FCFF'!K15/(1+D18)^9.5+'3 Forecast FCFF'!K15*(1+A20)/(D18-A20)/(1+D18)^10-('4 WACC'!B15-'4 WACC'!B16))/'4 WACC'!B17 -> 1797469.3 | E20: =('3 Forecast FCFF'!B15/(1+E18)^0.5+'3 Forecast FCFF'!C15/(1+E18)^1.5+'3 Forecast FCFF'!D15/(1+E18)^2.5+'3 Forecast FCFF'!E15/(1+E18)^3.5+'3 Forecast FCFF'!F15/(1+E18)^4.5+'3 Forecast FCFF'!G15/(1+E18)^5.5+'3 Forecast FCFF'!H15/(1+E18)^6.5+'3 Forecast FCFF'!I15/(1+E18)^7.5+'3 Forecast FCFF'!J15/(1+E18)^8.5+'3 Forecast FCFF'!K15/(1+E18)^9.5+'3 Forecast FCFF'!K15*(1+A20)/(E18-A20)/(1+E18)^10-('4 WACC'!B15-'4 WACC'!B16))/'4 WACC'!B17 -> 1460500.7 | F20: =('3 Forecast FCFF'!B15/(1+F18)^0.5+'3 Forecast FCFF'!C15/(1+F18)^1.5+'3 Forecast FCFF'!D15/(1+F18)^2.5+'3 Forecast FCFF'!E15/(1+F18)^3.5+'3 Forecast FCFF'!F15/(1+F18)^4.5+'3 Forecast FCFF'!G15/(1+F18)^5.5+'3 Forecast FCFF'!H15/(1+F18)^6.5+'3 Forecast FCFF'!I15/(1+F18)^7.5+'3 Forecast FCFF'!J15/(1+F18)^8.5+'3 Forecast FCFF'!K15/(1+F18)^9.5+'3 Forecast FCFF'!K15*(1+A20)/(F18-A20)/(1+F18)^10-('4 WACC'!B15-'4 WACC'!B16))/'4 WACC'!B17 -> 1228624.1
A21: ='1 Assumptions'!B14+(0) -> 0.025 | B21: =('3 Forecast FCFF'!B15/(1+B18)^0.5+'3 Forecast FCFF'!C15/(1+B18)^1.5+'3 Forecast FCFF'!D15/(1+B18)^2.5+'3 Forecast FCFF'!E15/(1+B18)^3.5+'3 Forecast FCFF'!F15/(1+B18)^4.5+'3 Forecast FCFF'!G15/(1+B18)^5.5+'3 Forecast FCFF'!H15/(1+B18)^6.5+'3 Forecast FCFF'!I15/(1+B18)^7.5+'3 Forecast FCFF'!J15/(1+B18)^8.5+'3 Forecast FCFF'!K15/(1+B18)^9.5+'3 Forecast FCFF'!K15*(1+A21)/(B18-A21)/(1+B18)^10-('4 WACC'!B15-'4 WACC'!B16))/'4 WACC'!B17 -> 3986508.5 | C21: =('3 Forecast FCFF'!B15/(1+C18)^0.5+'3 Forecast FCFF'!C15/(1+C18)^1.5+'3 Forecast FCFF'!D15/(1+C18)^2.5+'3 Forecast FCFF'!E15/(1+C18)^3.5+'3 Forecast FCFF'!F15/(1+C18)^4.5+'3 Forecast FCFF'!G15/(1+C18)^5.5+'3 Forecast FCFF'!H15/(1+C18)^6.5+'3 Forecast FCFF'!I15/(1+C18)^7.5+'3 Forecast FCFF'!J15/(1+C18)^8.5+'3 Forecast FCFF'!K15/(1+C18)^9.5+'3 Forecast FCFF'!K15*(1+A21)/(C18-A21)/(1+C18)^10-('4 WACC'!B15-'4 WACC'!B16))/'4 WACC'!B17 -> 2629599.1 | D21: =('3 Forecast FCFF'!B15/(1+D18)^0.5+'3 Forecast FCFF'!C15/(1+D18)^1.5+'3 Forecast FCFF'!D15/(1+D18)^2.5+'3 Forecast FCFF'!E15/(1+D18)^3.5+'3 Forecast FCFF'!F15/(1+D18)^4.5+'3 Forecast FCFF'!G15/(1+D18)^5.5+'3 Forecast FCFF'!H15/(1+D18)^6.5+'3 Forecast FCFF'!I15/(1+D18)^7.5+'3 Forecast FCFF'!J15/(1+D18)^8.5+'3 Forecast FCFF'!K15/(1+D18)^9.5+'3 Forecast FCFF'!K15*(1+A21)/(D18-A21)/(1+D18)^10-('4 WACC'!B15-'4 WACC'!B16))/'4 WACC'!B17 -> 1957182.3 | E21: =('3 Forecast FCFF'!B15/(1+E18)^0.5+'3 Forecast FCFF'!C15/(1+E18)^1.5+'3 Forecast FCFF'!D15/(1+E18)^2.5+'3 Forecast FCFF'!E15/(1+E18)^3.5+'3 Forecast FCFF'!F15/(1+E18)^4.5+'3 Forecast FCFF'!G15/(1+E18)^5.5+'3 Forecast FCFF'!H15/(1+E18)^6.5+'3 Forecast FCFF'!I15/(1+E18)^7.5+'3 Forecast FCFF'!J15/(1+E18)^8.5+'3 Forecast FCFF'!K15/(1+E18)^9.5+'3 Forecast FCFF'!K15*(1+A21)/(E18-A21)/(1+E18)^10-('4 WACC'!B15-'4 WACC'!B16))/'4 WACC'!B17 -> 1556396 | F21: =('3 Forecast FCFF'!B15/(1+F18)^0.5+'3 Forecast FCFF'!C15/(1+F18)^1.5+'3 Forecast FCFF'!D15/(1+F18)^2.5+'3 Forecast FCFF'!E15/(1+F18)^3.5+'3 Forecast FCFF'!F15/(1+F18)^4.5+'3 Forecast FCFF'!G15/(1+F18)^5.5+'3 Forecast FCFF'!H15/(1+F18)^6.5+'3 Forecast FCFF'!I15/(1+F18)^7.5+'3 Forecast FCFF'!J15/(1+F18)^8.5+'3 Forecast FCFF'!K15/(1+F18)^9.5+'3 Forecast FCFF'!K15*(1+A21)/(F18-A21)/(1+F18)^10-('4 WACC'!B15-'4 WACC'!B16))/'4 WACC'!B17 -> 1290743.3
A22: ='1 Assumptions'!B14+(0.005) -> 0.03 | B22: =('3 Forecast FCFF'!B15/(1+B18)^0.5+'3 Forecast FCFF'!C15/(1+B18)^1.5+'3 Forecast FCFF'!D15/(1+B18)^2.5+'3 Forecast FCFF'!E15/(1+B18)^3.5+'3 Forecast FCFF'!F15/(1+B18)^4.5+'3 Forecast FCFF'!G15/(1+B18)^5.5+'3 Forecast FCFF'!H15/(1+B18)^6.5+'3 Forecast FCFF'!I15/(1+B18)^7.5+'3 Forecast FCFF'!J15/(1+B18)^8.5+'3 Forecast FCFF'!K15/(1+B18)^9.5+'3 Forecast FCFF'!K15*(1+A22)/(B18-A22)/(1+B18)^10-('4 WACC'!B15-'4 WACC'!B16))/'4 WACC'!B17 -> 5142362 | C22: =('3 Forecast FCFF'!B15/(1+C18)^0.5+'3 Forecast FCFF'!C15/(1+C18)^1.5+'3 Forecast FCFF'!D15/(1+C18)^2.5+'3 Forecast FCFF'!E15/(1+C18)^3.5+'3 Forecast FCFF'!F15/(1+C18)^4.5+'3 Forecast FCFF'!G15/(1+C18)^5.5+'3 Forecast FCFF'!H15/(1+C18)^6.5+'3 Forecast FCFF'!I15/(1+C18)^7.5+'3 Forecast FCFF'!J15/(1+C18)^8.5+'3 Forecast FCFF'!K15/(1+C18)^9.5+'3 Forecast FCFF'!K15*(1+A22)/(C18-A22)/(1+C18)^10-('4 WACC'!B15-'4 WACC'!B16))/'4 WACC'!B17 -> 3049521.8 | D22: =('3 Forecast FCFF'!B15/(1+D18)^0.5+'3 Forecast FCFF'!C15/(1+D18)^1.5+'3 Forecast FCFF'!D15/(1+D18)^2.5+'3 Forecast FCFF'!E15/(1+D18)^3.5+'3 Forecast FCFF'!F15/(1+D18)^4.5+'3 Forecast FCFF'!G15/(1+D18)^5.5+'3 Forecast FCFF'!H15/(1+D18)^6.5+'3 Forecast FCFF'!I15/(1+D18)^7.5+'3 Forecast FCFF'!J15/(1+D18)^8.5+'3 Forecast FCFF'!K15/(1+D18)^9.5+'3 Forecast FCFF'!K15*(1+A22)/(D18-A22)/(1+D18)^10-('4 WACC'!B15-'4 WACC'!B16))/'4 WACC'!B17 -> 2162841.9 | E22: =('3 Forecast FCFF'!B15/(1+E18)^0.5+'3 Forecast FCFF'!C15/(1+E18)^1.5+'3 Forecast FCFF'!D15/(1+E18)^2.5+'3 Forecast FCFF'!E15/(1+E18)^3.5+'3 Forecast FCFF'!F15/(1+E18)^4.5+'3 Forecast FCFF'!G15/(1+E18)^5.5+'3 Forecast FCFF'!H15/(1+E18)^6.5+'3 Forecast FCFF'!I15/(1+E18)^7.5+'3 Forecast FCFF'!J15/(1+E18)^8.5+'3 Forecast FCFF'!K15/(1+E18)^9.5+'3 Forecast FCFF'!K15*(1+A22)/(E18-A22)/(1+E18)^10-('4 WACC'!B15-'4 WACC'!B16))/'4 WACC'!B17 -> 1673715.4 | F22: =('3 Forecast FCFF'!B15/(1+F18)^0.5+'3 Forecast FCFF'!C15/(1+F18)^1.5+'3 Forecast FCFF'!D15/(1+F18)^2.5+'3 Forecast FCFF'!E15/(1+F18)^3.5+'3 Forecast FCFF'!F15/(1+F18)^4.5+'3 Forecast FCFF'!G15/(1+F18)^5.5+'3 Forecast FCFF'!H15/(1+F18)^6.5+'3 Forecast FCFF'!I15/(1+F18)^7.5+'3 Forecast FCFF'!J15/(1+F18)^8.5+'3 Forecast FCFF'!K15/(1+F18)^9.5+'3 Forecast FCFF'!K15*(1+A22)/(F18-A22)/(1+F18)^10-('4 WACC'!B15-'4 WACC'!B16))/'4 WACC'!B17 -> 1364206.3
A23: ='1 Assumptions'!B14+(0.01) -> 0.035 | B23: =('3 Forecast FCFF'!B15/(1+B18)^0.5+'3 Forecast FCFF'!C15/(1+B18)^1.5+'3 Forecast FCFF'!D15/(1+B18)^2.5+'3 Forecast FCFF'!E15/(1+B18)^3.5+'3 Forecast FCFF'!F15/(1+B18)^4.5+'3 Forecast FCFF'!G15/(1+B18)^5.5+'3 Forecast FCFF'!H15/(1+B18)^6.5+'3 Forecast FCFF'!I15/(1+B18)^7.5+'3 Forecast FCFF'!J15/(1+B18)^8.5+'3 Forecast FCFF'!K15/(1+B18)^9.5+'3 Forecast FCFF'!K15*(1+A23)/(B18-A23)/(1+B18)^10-('4 WACC'!B15-'4 WACC'!B16))/'4 WACC'!B17 -> 7482423.2 | C23: =('3 Forecast FCFF'!B15/(1+C18)^0.5+'3 Forecast FCFF'!C15/(1+C18)^1.5+'3 Forecast FCFF'!D15/(1+C18)^2.5+'3 Forecast FCFF'!E15/(1+C18)^3.5+'3 Forecast FCFF'!F15/(1+C18)^4.5+'3 Forecast FCFF'!G15/(1+C18)^5.5+'3 Forecast FCFF'!H15/(1+C18)^6.5+'3 Forecast FCFF'!I15/(1+C18)^7.5+'3 Forecast FCFF'!J15/(1+C18)^8.5+'3 Forecast FCFF'!K15/(1+C18)^9.5+'3 Forecast FCFF'!K15*(1+A23)/(C18-A23)/(1+C18)^10-('4 WACC'!B15-'4 WACC'!B16))/'4 WACC'!B17 -> 3681949.9 | D23: =('3 Forecast FCFF'!B15/(1+D18)^0.5+'3 Forecast FCFF'!C15/(1+D18)^1.5+'3 Forecast FCFF'!D15/(1+D18)^2.5+'3 Forecast FCFF'!E15/(1+D18)^3.5+'3 Forecast FCFF'!F15/(1+D18)^4.5+'3 Forecast FCFF'!G15/(1+D18)^5.5+'3 Forecast FCFF'!H15/(1+D18)^6.5+'3 Forecast FCFF'!I15/(1+D18)^7.5+'3 Forecast FCFF'!J15/(1+D18)^8.5+'3 Forecast FCFF'!K15/(1+D18)^9.5+'3 Forecast FCFF'!K15*(1+A23)/(D18-A23)/(1+D18)^10-('4 WACC'!B15-'4 WACC'!B16))/'4 WACC'!B17 -> 2437606.2 | E23: =('3 Forecast FCFF'!B15/(1+E18)^0.5+'3 Forecast FCFF'!C15/(1+E18)^1.5+'3 Forecast FCFF'!D15/(1+E18)^2.5+'3 Forecast FCFF'!E15/(1+E18)^3.5+'3 Forecast FCFF'!F15/(1+E18)^4.5+'3 Forecast FCFF'!G15/(1+E18)^5.5+'3 Forecast FCFF'!H15/(1+E18)^6.5+'3 Forecast FCFF'!I15/(1+E18)^7.5+'3 Forecast FCFF'!J15/(1+E18)^8.5+'3 Forecast FCFF'!K15/(1+E18)^9.5+'3 Forecast FCFF'!K15*(1+A23)/(E18-A23)/(1+E18)^10-('4 WACC'!B15-'4 WACC'!B16))/'4 WACC'!B17 -> 1820541.2 | F23: =('3 Forecast FCFF'!B15/(1+F18)^0.5+'3 Forecast FCFF'!C15/(1+F18)^1.5+'3 Forecast FCFF'!D15/(1+F18)^2.5+'3 Forecast FCFF'!E15/(1+F18)^3.5+'3 Forecast FCFF'!F15/(1+F18)^4.5+'3 Forecast FCFF'!G15/(1+F18)^5.5+'3 Forecast FCFF'!H15/(1+F18)^6.5+'3 Forecast FCFF'!I15/(1+F18)^7.5+'3 Forecast FCFF'!J15/(1+F18)^8.5+'3 Forecast FCFF'!K15/(1+F18)^9.5+'3 Forecast FCFF'!K15*(1+A23)/(F18-A23)/(1+F18)^10-('4 WACC'!B15-'4 WACC'!B16))/'4 WACC'!B17 -> 1452432.5
A26: FOOTBALL FIELD — VALUATION RANGE SUMMARY
A27: Methodology | B27: Low ($) | C27: Base ($) | D27: High ($)
A28: DCF Valuation | B28: ='6 Sensitivity Dashboard'!B23 -> 7482423.2 | C28: ='5 DCF Valuation'!B24 -> 1957182.3 | D28: ='6 Sensitivity Dashboard'!F19 -> 1175409.6
A29: Current Market Price | B29: ='1 Assumptions'!B13 -> 0.04 | C29: ='1 Assumptions'!B13 -> 0.04 | D29: ='1 Assumptions'!B13 -> 0.04
A30: EV/EBITDA Implied (FY2025E) | B30: ='5 DCF Valuation'!B20/'3 Forecast FCFF'!B5 -> 13.506586 | C30: ='5 DCF Valuation'!B20/'3 Forecast FCFF'!B5 -> 13.506586 | D30: ='5 DCF Valuation'!B20/'3 Forecast FCFF'!B5 -> 13.506586
